ics_compare.py
remind.py
remind-0.19.2.dist-info/LICENSE
remind-0.19.2.dist-info/METADATA
remind-0.19.2.dist-info/WHEEL
remind-0.19.2.dist-info/entry_points.txt
remind-0.19.2.dist-info/top_level.txt
remind-0.19.2.dist-info/RECORD
