Metadata-Version: 2.1
Name: remind
Version: 0.19.2
Summary: Remind Python library
Home-page: https://github.com/jspricke/python-remind
Author: Jochen Sprickerhof
Author-email: remind@jochen.sprickerhof.de
License: GPLv3+
Keywords: Remind
Classifier: Programming Language :: Python
Classifier: Development Status :: 4 - Beta
Classifier: Environment :: Console
Classifier: License :: OSI Approved :: GNU General Public License v3 or later (GPLv3+)
Classifier: Topic :: Office/Business :: Scheduling
Classifier: Topic :: Software Development :: Libraries :: Python Modules
License-File: LICENSE
Requires-Dist: python-dateutil
Requires-Dist: vobject
